pymecht/MCMC.py
pymecht/MatModel.py
pymecht/ParamDict.py
pymecht/ParamFitter.py
pymecht/RandomParameters.py
pymecht/SampleExperiment.py
pymecht/__init__.py
pymecht/_version.py
pymecht-1.1.3.dist-info/LICENSE
pymecht-1.1.3.dist-info/METADATA
pymecht-1.1.3.dist-info/WHEEL
pymecht-1.1.3.dist-info/top_level.txt
pymecht-1.1.3.dist-info/RECORD
