Metadata-Version: 2.2
Name: pymecht
Version: 1.1.3
Summary: This is PYthon-based repository is for MECHanics of Tissue mechanics. The focus is on flexibility of adding new constitutive models and varying their parameters.
Author-email: Ankush Aggarwal <ankush.aggarwal@glasgow.ac.uk>, Ross Williams <ross.williams@glasgow.ac.uk>
Requires-Python: <3.13,>=3.8
License-File: LICENSE
Requires-Dist: matplotlib>=3.4.1
Requires-Dist: numpy>=1.22.2
Requires-Dist: pyDOE>=0.3.8
Requires-Dist: scipy>=1.8.0
Requires-Dist: torch>=1.13.1
Requires-Dist: sympy>=1.10.1
Requires-Dist: tqdm>=4.61.0
Requires-Dist: pandas>=1.2.4
Provides-Extra: dev
Requires-Dist: pytest>=7.2.0; extra == "dev"
